prototyping_inference_engine/__init__.py
prototyping_inference_engine/api/__init__.py
prototyping_inference_engine/api/atom/__init__.py
prototyping_inference_engine/api/atom/atom.py
prototyping_inference_engine/api/atom/atom_operations.py
prototyping_inference_engine/api/atom/predicate.py
prototyping_inference_engine/api/atom/set/__init__.py
prototyping_inference_engine/api/atom/set/atom_set.py
prototyping_inference_engine/api/atom/set/frozen_atom_set.py
prototyping_inference_engine/api/atom/set/mutable_atom_set.py
prototyping_inference_engine/api/atom/set/core/__init__.py
prototyping_inference_engine/api/atom/set/core/core_algorithm.py
prototyping_inference_engine/api/atom/set/core/core_algorithm_provider.py
prototyping_inference_engine/api/atom/set/core/naive_core_by_specialization.py
prototyping_inference_engine/api/atom/set/homomorphism/__init__.py
prototyping_inference_engine/api/atom/set/homomorphism/homomorphism_algorithm.py
prototyping_inference_engine/api/atom/set/homomorphism/homomorphism_algorithm_provider.py
prototyping_inference_engine/api/atom/set/homomorphism/backtrack/__init__.py
prototyping_inference_engine/api/atom/set/homomorphism/backtrack/naive_backtrack_homomorphism_algorithm.py
prototyping_inference_engine/api/atom/set/homomorphism/backtrack/scheduler/__init__.py
prototyping_inference_engine/api/atom/set/homomorphism/backtrack/scheduler/backtrack_scheduler.py
prototyping_inference_engine/api/atom/set/homomorphism/backtrack/scheduler/by_variable_and_domain_backtrack_scheduler.py
prototyping_inference_engine/api/atom/set/homomorphism/backtrack/scheduler/by_variable_backtrack_scheduler.py
prototyping_inference_engine/api/atom/set/homomorphism/backtrack/scheduler/dynamic_backtrack_scheduler.py
prototyping_inference_engine/api/atom/set/homomorphism/backtrack/scheduler/test/__init__.py
prototyping_inference_engine/api/atom/set/homomorphism/backtrack/scheduler/test/test_backtrack_scheduler.py
prototyping_inference_engine-0.0.13.dist-info/licenses/LICENSE
prototyping_inference_engine-0.0.13.dist-info/METADATA
prototyping_inference_engine-0.0.13.dist-info/WHEEL
prototyping_inference_engine-0.0.13.dist-info/entry_points.txt
prototyping_inference_engine-0.0.13.dist-info/top_level.txt
prototyping_inference_engine-0.0.13.dist-info/RECORD
