Metadata-Version: 2.4
Name: prototyping_inference_engine
Version: 0.0.13
Summary: A library to prototype inference engines with logical reasoning capabilities
Author-email: Guillaume Pérution-Kihli <guillaume.kihli@yahoo.fr>
License-Expression: GPL-3.0-or-later
Project-URL: Homepage, https://github.com/guillaumeki/pie
Project-URL: Repository, https://github.com/guillaumeki/pie
Project-URL: Documentation, https://github.com/guillaumeki/pie#readme
Project-URL: Issues, https://github.com/guillaumeki/pie/issues
Keywords: inference-engine,reasoning,datalog,knowledge-base,query-rewriting,backward-chaining,first-order-logic
Classifier: Development Status :: 3 - Alpha
Classifier: Intended Audience :: Developers
Classifier: Intended Audience :: Science/Research
Classifier: Topic :: Scientific/Engineering :: Artificial Intelligence
Classifier: Programming Language :: Python :: 3
Classifier: Programming Language :: Python :: 3.10
Classifier: Programming Language :: Python :: 3.11
Classifier: Programming Language :: Python :: 3.12
Classifier: Operating System :: OS Independent
Requires-Python: >=3.10
License-File: LICENSE
Requires-Dist: lark>=1.0
Provides-Extra: dev
Requires-Dist: build; extra == "dev"
Requires-Dist: twine; extra == "dev"
Dynamic: license-file
